MANIFEST.in
README.markdown
setup.py
scraptils/__init__.py
scraptils/alchemize.py
scraptils/asdf.py
scraptils/db_loader.py
scraptils/dump_schema.py
scraptils/io.py
scraptils/sqlize.py
scraptils/utils.py
scraptils.egg-info/PKG-INFO
scraptils.egg-info/SOURCES.txt
scraptils.egg-info/dependency_links.txt
scraptils.egg-info/entry_points.txt
scraptils.egg-info/top_level.txt
scraptils/datainspector/__init__.py
scraptils/datainspector/__main__.py
scraptils/tools/bbox.py
scraptils/tools/csvtojson.py
scraptils/tools/pdf2csv.py
scraptils/tools/pdfmask.sh
scraptils/tools/showcells.py
scraptils/tools/split.py