Metadata-Version: 1.1
Name: scraptils
Version: 0.2.2
Summary: Scraping and datamangling Utilities
Home-page: http://packages.python.org/scraptils
Author: Stefan Marsiske
Author-email: s@ctrlc.hu
License: AGPLv3+
Keywords: scraping data
Platform: UNKNOWN
Classifier: Development Status :: 4 - Beta
Classifier: License :: OSI Approved :: GNU Affero General Public License v3
Classifier: Environment :: Web Environment
